MANIFEST.in
README.rst
dev-requirements.txt
requirements.txt
setup.py
test-requirements.txt
nonobvious/__init__.py
nonobvious/entities.py
nonobvious/fields.py
nonobvious.egg-info/PKG-INFO
nonobvious.egg-info/SOURCES.txt
nonobvious.egg-info/dependency_links.txt
nonobvious.egg-info/not-zip-safe
nonobvious.egg-info/requires.txt
nonobvious.egg-info/top_level.txt