Metadata-Version: 1.1
Name: nonobvious
Version: 0.1
Summary: A simple, but non-obvious approach to setting boundaries.
Home-page: http://github.com/eykd/nonobvious
Author: David Eyk
Author-email: david.eyk@gmail.com
License: BSD
Platform: UNKNOWN
Classifier: Development Status :: 4 - Beta
Classifier: Intended Audience :: Developers
Classifier: License :: OSI Approved :: BSD License
Classifier: Natural Language :: English
Classifier: Topic :: Software Development :: Libraries
